vagrantgen/Vagrantfile.j2
vagrantgen/__init__.py
vagrantgen/ansible-inventory.j2
vagrantgen/vagrant-template.yaml
vagrantgen-0.5.dist-info/LICENSE
vagrantgen-0.5.dist-info/METADATA
vagrantgen-0.5.dist-info/WHEEL
vagrantgen-0.5.dist-info/entry_points.txt
vagrantgen-0.5.dist-info/top_level.txt
vagrantgen-0.5.dist-info/RECORD
