Metadata-Version: 2.1
Name: vagrantgen
Version: 0.5
Summary: Vagrantfile generator
Home-page: https://github.com/aramcap/vagrantgen
Author: Adrian Ramos
License: LICENSE
Platform: UNKNOWN
Classifier: Environment :: Console
Classifier: Development Status :: 4 - Beta
Classifier: Programming Language :: Python :: 3
License-File: LICENSE
Requires-Dist: importlib-resources
Requires-Dist: pyyaml
